redgrease/__init__.py
redgrease/cli.py
redgrease/client.py
redgrease/config.py
redgrease/data.py
redgrease/exceptions.py
redgrease/formatting.py
redgrease/func.py
redgrease/gearialization.py
redgrease/gears.py
redgrease/hysteresis.py
redgrease/loader.py
redgrease/reader.py
redgrease/requirements.py
redgrease/runtime.py
redgrease/runtime_client.py
redgrease/sugar.py
redgrease/typing.py
redgrease/utils.py
redgrease-0.3.30.dist-info/LICENSE
redgrease-0.3.30.dist-info/METADATA
redgrease-0.3.30.dist-info/WHEEL
redgrease-0.3.30.dist-info/entry_points.txt
redgrease-0.3.30.dist-info/top_level.txt
redgrease-0.3.30.dist-info/RECORD
