Metadata-Version: 2.1
Name: redgrease
Version: 0.3.30
Summary: RedisGears helper package
Home-page: https://github.com/lyngon/redgrease
Author: Anders Åström
Author-email: anders@lyngon.com
License: MIT License
Keywords: Redis,Gears,development
Platform: UNKNOWN
Classifier: Programming Language :: Python :: 3 :: Only
Classifier: Programming Language :: Python :: 3.6
Classifier: Programming Language :: Python :: 3.7
Classifier: Programming Language :: Python :: 3.8
Classifier: Programming Language :: Python :: 3.9
Classifier: License :: OSI Approved :: MIT License
Classifier: Operating System :: OS Independent
Classifier: Development Status :: 3 - Alpha
Classifier: Intended Audience :: Developers
Classifier: Topic :: Database
Classifier: Topic :: Software Development
Classifier: Topic :: Software Development :: Libraries :: Application Frameworks
Requires-Python: >=3.6
Provides-Extra: all
Requires-Dist: attrs ; extra == 'all'
Requires-Dist: redis ; extra == 'all'
Requires-Dist: cloudpickle ; extra == 'all'
Requires-Dist: packaging ; extra == 'all'
Requires-Dist: wrapt ; extra == 'all'
Requires-Dist: typing-extensions ; extra == 'all'
Requires-Dist: redis-py-cluster ; extra == 'all'
Requires-Dist: watchdog ; extra == 'all'
Requires-Dist: ConfigArgParse ; extra == 'all'
Requires-Dist: pyyaml ; extra == 'all'
Provides-Extra: cli
Requires-Dist: attrs ; extra == 'cli'
Requires-Dist: redis ; extra == 'cli'
Requires-Dist: cloudpickle ; extra == 'cli'
Requires-Dist: packaging ; extra == 'cli'
Requires-Dist: wrapt ; extra == 'cli'
Requires-Dist: typing-extensions ; extra == 'cli'
Requires-Dist: redis-py-cluster ; extra == 'cli'
Requires-Dist: watchdog ; extra == 'cli'
Requires-Dist: ConfigArgParse ; extra == 'cli'
Requires-Dist: pyyaml ; extra == 'cli'
Provides-Extra: client
Requires-Dist: attrs ; extra == 'client'
Requires-Dist: redis ; extra == 'client'
Requires-Dist: cloudpickle ; extra == 'client'
Requires-Dist: packaging ; extra == 'client'
Requires-Dist: wrapt ; extra == 'client'
Requires-Dist: typing-extensions ; extra == 'client'
Requires-Dist: redis-py-cluster ; extra == 'client'
Provides-Extra: runtime
Requires-Dist: attrs ; extra == 'runtime'
Requires-Dist: redis ; extra == 'runtime'
Requires-Dist: cloudpickle ; extra == 'runtime'
Requires-Dist: packaging ; extra == 'runtime'
Requires-Dist: wrapt ; extra == 'runtime'
